musort/__init__.py
musort/__main__.py
musort/info.py
musort/sort_files.py
musort/sort_folders.py
musort/tools/__init__.py
musort/tools/clargparser.py
musort/tools/os_locale/__init__.py
musort/tools/os_locale/linux.py
musort/tools/os_locale/windows.py
musort-0.2.0.data/scripts/musort
musort-0.2.0.dist-info/LICENSE
musort-0.2.0.dist-info/METADATA
musort-0.2.0.dist-info/WHEEL
musort-0.2.0.dist-info/top_level.txt
musort-0.2.0.dist-info/RECORD
