Metadata-Version: 2.1
Name: musort
Version: 0.2.0
Summary: A music-sorting package.
Home-page: https://github.com/ernieIzde8ski/mus_sort
Author: Ernest Izdebski
License: MIT
Classifier: Development Status :: 5 - Production/Stable
Classifier: License :: OSI Approved :: MIT License
Classifier: Natural Language :: English
Classifier: Operating System :: OS Independent
Classifier: Programming Language :: Python :: 3.9
Classifier: Programming Language :: Python :: 3.10
Classifier: Programming Language :: Python :: 3.11
Classifier: Topic :: Utilities
Classifier: Typing :: Typed
Requires-Python: >=3.9.0
License-File: LICENSE
Requires-Dist: tinytag (>=1.8.1)
Requires-Dist: typed-argument-parser (>=1.7.2)
